pytubemusic/__init__.py
pytubemusic/__main__.py
pytubemusic/logging/__init__.py
pytubemusic/logging/logs.py
pytubemusic/model/__init__.py
pytubemusic/model/types.py
pytubemusic/model/audio/__init__.py
pytubemusic/model/audio/audio.py
pytubemusic/model/track/__init__.py
pytubemusic/model/track/track_data.py
pytubemusic/model/user/__init__.py
pytubemusic/model/user/album.py
pytubemusic/model/user/base.py
pytubemusic/model/user/cover.py
pytubemusic/model/user/root.py
pytubemusic/model/user/tags.py
pytubemusic/model/user/track.py
pytubemusic/streams/__init__.py
pytubemusic/streams/audio.py
pytubemusic/streams/images.py
pytubemusic/streams/track.py
pytubemusic/streams/utils.py
pytubemusic-0.7.0.dist-info/LICENSE
pytubemusic-0.7.0.dist-info/METADATA
pytubemusic-0.7.0.dist-info/WHEEL
pytubemusic-0.7.0.dist-info/entry_points.txt
pytubemusic-0.7.0.dist-info/top_level.txt
pytubemusic-0.7.0.dist-info/RECORD
