Metadata-Version: 2.2
Name: pytubemusic
Version: 0.7.0
Summary: A cli that may or may not download albums from a certain website
License: MIT License
Project-URL: repository, https://github.com/James-Ansley/pytubemusic
Classifier: Development Status :: 1 - Planning
Classifier: Topic :: Utilities
Classifier: Programming Language :: Python :: 3
Classifier: License :: OSI Approved :: MIT License
Requires-Python: >=3.12
License-File: LICENSE
Requires-Dist: pydantic~=2.10.0
Requires-Dist: pydub~=0.25.1
Requires-Dist: arguably~=1.3.0
Requires-Dist: pytubefix~=8.12.1
Requires-Dist: audioop-lts~=0.2.1
